studio/__init__.py
studio/client.py
studio/datasets.py
studio/experiments.py
studio/logs.py
studio/urls.py
studio/util.py
superpipe_studio-0.0.4.dist-info/METADATA
superpipe_studio-0.0.4.dist-info/WHEEL
superpipe_studio-0.0.4.dist-info/RECORD
