Metadata-Version: 2.1
Name: superpipe-studio
Version: 0.0.4
Summary: 
Home-page: https://github.com/villagecomputing/superpipe-studio
License: MIT
Author: Aman Dhesi
Author-email: aman@stelolabs.com
Requires-Python: >=3.10,<4.0
Classifier: License :: OSI Approved :: MIT License
Classifier: Programming Language :: Python :: 3
Classifier: Programming Language :: Python :: 3.10
Classifier: Programming Language :: Python :: 3.11
Requires-Dist: httpx (>=0.27.0,<0.28.0)
Requires-Dist: pandas (>=2.2.2,<3.0.0)
Project-URL: Repository, https://github.com/villagecomputing/superpipe-studio
